<annotation>
	<folder>train</folder>
	<filename>00000252_jpg.rf.8f535f1d918612147eccbb43dd207e6d.jpg</filename>
	<path>/home/cpow/Desktop/eageleeyes/dataset/roboflow/train/00000252_jpg.rf.8f535f1d918612147eccbb43dd207e6d.jpg</path>
	<source>
		<database>Unknown</database>
	</source>
	<size>
		<width>256</width>
		<height>256</height>
		<depth>3</depth>
	</size>
	<segmented>0</segmented>
	<object>
		<name>low quality vest</name>
		<pose>Unspecified</pose>
		<truncated>0</truncated>
		<difficult>0</difficult>
		<bndbox>
			<xmin>20</xmin>
			<ymin>120</ymin>
			<xmax>38</xmax>
			<ymax>152</ymax>
		</bndbox>
	</object>
	<object>
		<name>hat</name>
		<pose>Unspecified</pose>
		<truncated>0</truncated>
		<difficult>0</difficult>
		<bndbox>
			<xmin>22</xmin>
			<ymin>105</ymin>
			<xmax>35</xmax>
			<ymax>118</ymax>
		</bndbox>
	</object>
	<object>
		<name>hat</name>
		<pose>Unspecified</pose>
		<truncated>0</truncated>
		<difficult>0</difficult>
		<bndbox>
			<xmin>60</xmin>
			<ymin>115</ymin>
			<xmax>67</xmax>
			<ymax>124</ymax>
		</bndbox>
	</object>
	<object>
		<name>hat</name>
		<pose>Unspecified</pose>
		<truncated>0</truncated>
		<difficult>0</difficult>
		<bndbox>
			<xmin>120</xmin>
			<ymin>105</ymin>
			<xmax>129</xmax>
			<ymax>112</ymax>
		</bndbox>
	</object>
</annotation>
